{
    "photo-1": ".+?.(jpg|png);.+?;.+",
    "photo-2": ".+?.(jpg|png);.+?;.+",
    "photo-3": ".+?.(jpg|png);.+?;.+",
    "photo-4": ".+?.(jpg|png);.+?;.+",
    "photo-5": ".+?.(jpg|png);.+?;.+",
    "photo-6": ".+?.(jpg|png);.+?;.+",
    "photo-7": ".+?.(jpg|png);.+?;.+",
    "photo-8": ".+?.(jpg|png);.+?;.+",
    "photo-9": ".+?.(jpg|png);.+?;.+",
    "photo-10": ".+?.(jpg|png);.+?;.+",
    "photo-11": ".+?.(jpg|png);.+?;.+",
    "photo-12": ".+?.(jpg|png);.+?;.+",
    "photo-13": ".+?.(jpg|png);.+?;.+",
    "photo-14": ".+?.(jpg|png);.+?;.+",
    "photo-15": ".+?.(jpg|png);.+?;.+",
    "photo-16": ".+?.(jpg|png);.+?;.+",
    "photo-17": ".+?.(jpg|png);.+?;.+",
    "photo-18": ".+?.(jpg|png);.+?;.+",
    "photo-19": ".+?.(jpg|png);.+?;.+",
    "photo-20": ".+?.(jpg|png);.+?;.+",
    "scale-mode": [
        "fill",
        "fit"
    ],
    "dim-color": "#color",
    "caption": "?",
    "subcaption": "?",
    "caption-font": "#font",
    "caption-font-family": "#font-family",
    "caption-font-size": "#font-size",
    "caption-font-weight": [
        "normal",
        "bold"
    ],
    "caption-font-style": [
        "normal",
        "italic"
    ],
    "caption-font-no-scale": [
        "yes",
        "no"
    ],
    "subcaption-font": "#font",
    "subcaption-font-family": "#font-family",
    "subcaption-font-size": "#font-size",
    "subcaption-font-weight": [
        "normal",
        "bold"
    ],
    "subcaption-font-style": [
        "normal",
        "italic"
    ],
    "subcaption-font-no-scale": [
        "yes",
        "no"
    ],
    "caption-align": [
        "left",
        "right",
        "center"
    ],
    "caption-height": "?",
    "inner-caption": [
        "yes",
        "no"
    ],
    "caption-color": "#color",
    "subcaption-color": "#color",
    "caption-background-color": "#color"
}